easy_code_reader/__main__.py
easy_code_reader/config.py
easy_code_reader/decompiler.py
easy_code_reader/server.py
easy_code_reader/decompilers/cfr.jar
easy_code_reader/decompilers/fernflower.jar
easy_code_reader-1.3.1.dist-info/licenses/LICENSE
easy_code_reader-1.3.1.dist-info/METADATA
easy_code_reader-1.3.1.dist-info/WHEEL
easy_code_reader-1.3.1.dist-info/entry_points.txt
easy_code_reader-1.3.1.dist-info/top_level.txt
easy_code_reader-1.3.1.dist-info/RECORD
