Metadata-Version: 2.4
Name: easy-code-reader
Version: 1.3.1
Summary: A powerful MCP (Model Context Protocol) server for intelligently reading Java source code.
Author-email: FangYuan33 <ylwork33@163.com>
Maintainer-email: FangYuan33 <ylwork33@163.com>
License: Apache-2.0
Project-URL: Homepage, https://github.com/FangYuan33/easy-code-reader
Project-URL: Documentation, https://github.com/FangYuan33/easy-code-reader#readme
Project-URL: Repository, https://github.com/FangYuan33/easy-code-reader.git
Project-URL: Issues, https://github.com/FangYuan33/easy-code-reader/issues
Project-URL: Changelog, https://github.com/FangYuan33/easy-code-reader/releases
Keywords: mcp,model-context-protocol,maven,jar,java,decompiler,source-code,fernflower,claude,ai-tools
Classifier: Development Status :: 4 - Beta
Classifier: Intended Audience :: Developers
Classifier: License :: OSI Approved :: Apache Software License
Classifier: Programming Language :: Python :: 3
Classifier: Programming Language :: Python :: 3.10
Classifier: Programming Language :: Python :: 3.11
Classifier: Programming Language :: Python :: 3.12
Classifier: Programming Language :: Java
Classifier: Topic :: Software Development :: Libraries :: Python Modules
Classifier: Topic :: Software Development :: Build Tools
Classifier: Topic :: Utilities
Requires-Python: >=3.10
License-File: LICENSE
Requires-Dist: mcp>=0.9.0
Provides-Extra: dev
Requires-Dist: pytest>=7.0.0; extra == "dev"
Requires-Dist: pytest-asyncio>=0.21.0; extra == "dev"
Requires-Dist: build>=1.0.0; extra == "dev"
Requires-Dist: twine>=4.0.0; extra == "dev"
Dynamic: license-file
